my_deribit_api/__about__.py
my_deribit_api/__init__.py
my_deribit_api/constant.py
my_deribit_api/deribit_api.py
my_deribit_api/deribit_websocket.py
my_deribit_api-1.0.0.dist-info/METADATA
my_deribit_api-1.0.0.dist-info/WHEEL
my_deribit_api-1.0.0.dist-info/licenses/LICENSE.txt
my_deribit_api-1.0.0.dist-info/RECORD
