Metadata-Version: 2.3
Name: my-deribit-api
Version: 1.0.0
Project-URL: Documentation, https://github.com/unknown/my-deribit-api#readme
Project-URL: Issues, https://github.com/unknown/my-deribit-api/issues
Project-URL: Source, https://github.com/unknown/my-deribit-api
Author-email: liuyanzhi08 <702368372@qq.com>
License-Expression: MIT
License-File: LICENSE.txt
Classifier: Development Status :: 4 - Beta
Classifier: Programming Language :: Python
Classifier: Programming Language :: Python :: 3.8
Classifier: Programming Language :: Python :: 3.9
Classifier: Programming Language :: Python :: 3.10
Classifier: Programming Language :: Python :: 3.11
Classifier: Programming Language :: Python :: 3.12
Classifier: Programming Language :: Python :: Implementation :: CPython
Classifier: Programming Language :: Python :: Implementation :: PyPy
Requires-Python: >=3.8
